LICENSE
MANIFEST.in
README.rst
requirements.txt
setup.py
glvi/__init__.py
glvi/meda.py
glvi/todi.py
glvi.egg-info/PKG-INFO
glvi.egg-info/SOURCES.txt
glvi.egg-info/dependency_links.txt
glvi.egg-info/not-zip-safe
glvi.egg-info/requires.txt
glvi.egg-info/top_level.txt