Metadata-Version: 2.1
Name: glvi
Version: 0.1.7
Summary: Local variable importance from a global model
Home-page: https://github.com/PowderL/Local-variable-importance-from-a-global-mode
Author: TaoLi
Author-email: lp1559345469@gmail.com
License: UNKNOWN
Keywords: random forests variable importance
Platform: UNKNOWN
Classifier: Programming Language :: Python :: 3
Classifier: Programming Language :: Python :: 3.6
Classifier: Programming Language :: Python :: 3.7
Classifier: Programming Language :: Python :: 3.8
Classifier: Intended Audience :: Science/Research
Classifier: Operating System :: Microsoft :: Windows :: Windows 10
Classifier: Operating System :: POSIX
Classifier: Operating System :: Unix
Classifier: Operating System :: MacOS
Classifier: License :: Freeware
Classifier: Natural Language :: English
Requires-Python: >=3.6
